Metadata-Version: 2.4
Name: hsr1
Version: 1.3.1
Summary: graphing and data analysis for HSR-1 instruments
Requires-Python: >=3.10
License-File: LICENSE
Requires-Dist: numpy>=1.24
Requires-Dist: pandas>=1.5
Requires-Dist: matplotlib>=3.6
Requires-Dist: scipy>=1.10
Requires-Dist: lmfit>=1.1
Requires-Dist: ephem>=4.1
Requires-Dist: pvlib>=0.10
Provides-Extra: sg2
Requires-Dist: sg2; extra == "sg2"
Dynamic: license-file
